creditcards/__init__.py
creditcards/forms.py
creditcards/models.py
creditcards/types.py
creditcards/utils.py
creditcards/validators.py
creditcards/widgets.py
django_credit_cards-0.4.1.dist-info/LICENSE.txt
django_credit_cards-0.4.1.dist-info/METADATA
django_credit_cards-0.4.1.dist-info/WHEEL
django_credit_cards-0.4.1.dist-info/top_level.txt
django_credit_cards-0.4.1.dist-info/RECORD
