Metadata-Version: 2.1
Name: django-credit-cards
Version: 0.4.1
Summary: A Django app providing database and form fields for credit cards.
Home-page: https://github.com/dldevinc/django-credit-cards
Author: Mihail Mishakin
Author-email: x896321475@gmail.com
License: BSD
Keywords: django,creditcards
Platform: UNKNOWN
Classifier: Development Status :: 4 - Beta
Classifier: Environment :: Web Environment
Classifier: Framework :: Django
Classifier: Intended Audience :: Developers
Classifier: License :: OSI Approved :: MIT License
Classifier: Operating System :: OS Independent
Classifier: Programming Language :: Python
Classifier: Programming Language :: Python :: 3
Classifier: Topic :: Software Development :: Libraries :: Python Modules
Requires-Python: >=3
